{"meta":{"start":"2025Q1","end":"2027Q4","note":"Emulator output (15 Oct 2025 OBR model code). Deltas are shocked-minus-control with identical model structure in both runs. Under the demand closure the shock lands directly in the GDP identity and the behavioural second round is largely inactive, so the impact multiplier is ~1 by construction (the OBR's own published impact multiplier for current spending is ~0.45). Corporation-tax scenarios are excluded: their closure does not solve stably in this emulator. Illustrative, not an OBR forecast."},"periods":["2025Q1","2025Q2","2025Q3","2025Q4","2026Q1","2026Q2","2026Q3","2026Q4","2027Q1","2027Q2","2027Q3","2027Q4"],"variables":[{"code":"GDPM","label":"Real GDP","unit":"\u00a3bn"},{"code":"CONS","label":"Household consumption","unit":"\u00a3bn"},{"code":"IF","label":"Total investment","unit":"\u00a3bn"},{"code":"IBUS","label":"Business investment","unit":"\u00a3bn"},{"code":"ETLFS","label":"Employment","unit":"000s jobs"},{"code":"LFSUR","label":"Unemployment rate","unit":"pp"},{"code":"CPI","label":"Consumer prices (CPI)","unit":"% vs base"},{"code":"RHHDI","label":"Real household income","unit":"\u00a3bn"}],"scenarios":[{"id":"gov_spend","name":"\u00a35bn government spending","tag":"Demand","var":"CGG","shock":"CGG +\u00a31.25bn/qtr","closure":"standard","series":{"GDPM":[1.25,1.2502,1.2501,1.25,1.2498,1.2496,1.246,1.2463,1.247,1.2478,1.6289,1.6203],"CONS":[0.0,0.0002,0.0001,0.0,-0.0002,-0.0004,-0.004,-0.0037,-0.003,-0.0022,0.3789,0.3703],"IBUS":[0.0,0.0003,0.002,-0.0089,-0.0105,0.0087,0.0136,0.0082,0.0168,-0.0566,-0.0292,1.099],"RHHDI":[0.0,-0.0005,-0.0013,-0.0035,-0.0054,-0.0119,0.007,0.0055,0.0192,0.0999,-1.0846,-0.3546]}},{"id":"austerity","name":"\u00a310bn spending cut (austerity)","tag":"Demand","var":"CGG","shock":"CGG \u2212\u00a32.5bn/qtr","closure":"standard","series":{"GDPM":[-2.5,-2.5003,-2.5001,-2.5,-2.4996,-2.4992,-2.4919,-2.4927,-2.4941,-2.4956,-3.2833,-3.26],"CONS":[0.0,-0.0003,-0.0001,-0.0,0.0004,0.0008,0.0081,0.0073,0.0059,0.0044,-0.7833,-0.76]}},{"id":"export_cut","name":"\u00a310bn export slump","tag":"Demand","var":"X","shock":"X \u2212\u00a32.5bn/qtr","closure":"standard","series":{"GDPM":[-2.4297,-3.1418,-2.6482,-2.4805,-25.1373,-49.7843,-64.0185,-55.6984,-48.2553,-43.3325,-51.2038,-49.4487],"CONS":[0.0703,-0.6418,-0.1482,0.0195,-22.6373,-47.2843,-61.5185,-53.1984,-45.7553,-40.8325,-48.7038,-46.9487],"IBUS":[1.4312,-5.2088,-24.6134,5.9989,-600.319,-514.0888,-471.6177,-259.8652,-30.2572,116.3513,119.1673,-130.9401]}}]}